{
  "ID": "3a1e072a-77d9-41d5-ae5f-d2966d4f8a77",
  "Root": {
    "alive": true,
    "content": [
      "012d8753-9887-44cf-808b-8fe64f8b9fcd",
      "d7b0c860-fdce-4e87-8bf4-969dbd003a78",
      "b2d83c26-dd99-44cb-9a83-7fed6379b698"
    ],
    "created_by": "bb760e2d-d679-4b64-b2a9-03005b21870a",
    "created_time": 1550444818964,
    "id": "3a1e072a-77d9-41d5-ae5f-d2966d4f8a77",
    "ignore_block_count": true,
    "last_edited_by": "bb760e2d-d679-4b64-b2a9-03005b21870a",
    "last_edited_time": 1550444818964,
    "parent_id": "b698fa46-dece-4676-a681-eecc1a3388d2",
    "parent_table": "block",
    "properties": {
      "title": [
        [
          "030 How to add dividers using and DividerItemDecoration"
        ]
      ]
    },
    "type": "page",
    "version": 1,
    "content_resolved": [
      {
        "alive": true,
        "created_by": "bb760e2d-d679-4b64-b2a9-03005b21870a",
        "created_time": 1550444818963,
        "id": "012d8753-9887-44cf-808b-8fe64f8b9fcd",
        "ignore_block_count": true,
        "last_edited_by": "bb760e2d-d679-4b64-b2a9-03005b21870a",
        "last_edited_time": 1550444818963,
        "parent_id": "3a1e072a-77d9-41d5-ae5f-d2966d4f8a77",
        "parent_table": "block",
        "properties": {
          "title": [
            [
              "The "
            ],
            [
              "DividerItemDecoration",
              [
                [
                  "c"
                ],
                [
                  "a",
                  "https://developer.android.com/reference/android/support/v7/widget/DividerItemDecoration.html"
                ]
              ]
            ],
            [
              " is a "
            ],
            [
              "RecyclerView.ItemDecoration",
              [
                [
                  "c"
                ]
              ]
            ],
            [
              " that can be used as a divider between items."
            ]
          ]
        },
        "type": "text",
        "version": 1,
        "inline_content": [
          {
            "Text": "The "
          },
          {
            "Text": "DividerItemDecoration",
            "AttrFlags": 2,
            "Link": "https://developer.android.com/reference/android/support/v7/widget/DividerItemDecoration.html"
          },
          {
            "Text": " is a "
          },
          {
            "Text": "RecyclerView.ItemDecoration",
            "AttrFlags": 2
          },
          {
            "Text": " that can be used as a divider between items."
          }
        ]
      },
      {
        "alive": true,
        "created_by": "bb760e2d-d679-4b64-b2a9-03005b21870a",
        "created_time": 1550444818964,
        "id": "d7b0c860-fdce-4e87-8bf4-969dbd003a78",
        "ignore_block_count": true,
        "last_edited_by": "bb760e2d-d679-4b64-b2a9-03005b21870a",
        "last_edited_time": 1550444818964,
        "parent_id": "3a1e072a-77d9-41d5-ae5f-d2966d4f8a77",
        "parent_table": "block",
        "properties": {
          "language": [
            [
              "Plain Text"
            ]
          ],
          "title": [
            [
              "DividerItemDecoration mDividerItemDecoration = new DividerItemDecoration(context,\n             mLayoutManager.getOrientation());\nrecyclerView.addItemDecoration(mDividerItemDecoration);"
            ]
          ]
        },
        "type": "code",
        "version": 1,
        "code": "DividerItemDecoration mDividerItemDecoration = new DividerItemDecoration(context,\n             mLayoutManager.getOrientation());\nrecyclerView.addItemDecoration(mDividerItemDecoration);",
        "code_language": "Plain Text"
      },
      {
        "alive": true,
        "created_by": "bb760e2d-d679-4b64-b2a9-03005b21870a",
        "created_time": 1550444818964,
        "id": "b2d83c26-dd99-44cb-9a83-7fed6379b698",
        "ignore_block_count": true,
        "last_edited_by": "bb760e2d-d679-4b64-b2a9-03005b21870a",
        "last_edited_time": 1550444818964,
        "parent_id": "3a1e072a-77d9-41d5-ae5f-d2966d4f8a77",
        "parent_table": "block",
        "properties": {
          "title": [
            [
              "It supports both orientation using "
            ],
            [
              "DividerItemDecoration.VERTICAL",
              [
                [
                  "c"
                ]
              ]
            ],
            [
              " and "
            ],
            [
              "DividerItemDecoration.HORIZONTAL",
              [
                [
                  "c"
                ]
              ]
            ],
            [
              "."
            ]
          ]
        },
        "type": "text",
        "version": 1,
        "inline_content": [
          {
            "Text": "It supports both orientation using "
          },
          {
            "Text": "DividerItemDecoration.VERTICAL",
            "AttrFlags": 2
          },
          {
            "Text": " and "
          },
          {
            "Text": "DividerItemDecoration.HORIZONTAL",
            "AttrFlags": 2
          },
          {
            "Text": "."
          }
        ]
      }
    ],
    "title": "030 How to add dividers using and DividerItemDecoration"
  },
  "Users": [
    {
      "email": "kkowalczyk@gmail.com",
      "family_name": "Kowalczyk",
      "given_name": "Krzysztof",
      "id": "bb760e2d-d679-4b64-b2a9-03005b21870a",
      "locale": "en",
      "mobile_onboarding_completed": true,
      "onboarding_completed": true,
      "profile_photo": "https://s3-us-west-2.amazonaws.com/public.notion-static.com/2dcaa66c-7674-4ff6-9924-601785b63561/head-bw-640x960.png",
      "time_zone": "America/Los_Angeles",
      "version": 18
    }
  ],
  "Tables": null
}