{
  "ID": "4f6441ec-a8f8-4e36-ab7c-b03f37c7ca89",
  "Root": {
    "alive": true,
    "content": [
      "7a192eff-780b-4dfe-8778-197af0173293",
      "bdea53cd-e4d8-4712-946e-35fa75055ef1",
      "bc1f7ae7-afbb-4b1a-a130-bef1da3afe1f",
      "2282b347-fc0e-4d1b-8605-0d061141a8e2",
      "c485d9fa-dc6b-43ed-905b-1ea7ab9644d3",
      "2aeba1ed-f284-4404-b9c2-1a3a4eef204d",
      "1ada0a9e-948a-489c-a0a6-b29db32b4c0a",
      "b0970e9b-1236-4428-ae7f-0b4e7c075c0f",
      "9a3c0368-2480-4f05-b741-77503d33ddad",
      "0144877d-1baf-4d31-abba-9947a7b0eb8b",
      "6f4a90d3-bbdf-4562-a326-ef73a431f69e"
    ],
    "created_by": "bb760e2d-d679-4b64-b2a9-03005b21870a",
    "created_time": 1550522298730,
    "format": {
      "page_full_width": true,
      "page_small_text": true
    },
    "id": "4f6441ec-a8f8-4e36-ab7c-b03f37c7ca89",
    "ignore_block_count": true,
    "last_edited_by": "bb760e2d-d679-4b64-b2a9-03005b21870a",
    "last_edited_time": 1550655120000,
    "parent_id": "83f01298-2804-4599-8deb-99728a5d557a",
    "parent_table": "block",
    "properties": {
      "title": [
        [
          "Include Guards"
        ]
      ]
    },
    "type": "page",
    "version": 8,
    "content_resolved": [
      {
        "alive": true,
        "created_by": "bb760e2d-d679-4b64-b2a9-03005b21870a",
        "created_time": 1550522298722,
        "id": "7a192eff-780b-4dfe-8778-197af0173293",
        "ignore_block_count": true,
        "last_edited_by": "bb760e2d-d679-4b64-b2a9-03005b21870a",
        "last_edited_time": 1550522298722,
        "parent_id": "4f6441ec-a8f8-4e36-ab7c-b03f37c7ca89",
        "parent_table": "block",
        "properties": {
          "title": [
            [
              "A header file may be included by other header files. A source file (compilation unit) that includes multiple headers may therefore, indirectly, include some headers more than once. If such a header file that is included more than once contains definitions, the compiler (after preprocessing) detects a violation of the One Definition Rule (e.g. §3.2 of the 2003 C++ standard) and therefore issues a diagnostic and compilation fails."
            ]
          ]
        },
        "type": "text",
        "version": 1,
        "inline_content": [
          {
            "Text": "A header file may be included by other header files. A source file (compilation unit) that includes multiple headers may therefore, indirectly, include some headers more than once. If such a header file that is included more than once contains definitions, the compiler (after preprocessing) detects a violation of the One Definition Rule (e.g. §3.2 of the 2003 C++ standard) and therefore issues a diagnostic and compilation fails."
          }
        ]
      },
      {
        "alive": true,
        "created_by": "bb760e2d-d679-4b64-b2a9-03005b21870a",
        "created_time": 1550522298725,
        "id": "bdea53cd-e4d8-4712-946e-35fa75055ef1",
        "ignore_block_count": true,
        "last_edited_by": "bb760e2d-d679-4b64-b2a9-03005b21870a",
        "last_edited_time": 1550522298725,
        "parent_id": "4f6441ec-a8f8-4e36-ab7c-b03f37c7ca89",
        "parent_table": "block",
        "properties": {
          "title": [
            [
              "Multiple inclusion is prevented using “include guards”, which are sometimes also known as header guards or macro guards. These are implemented using the preprocessor "
            ],
            [
              "#define",
              [
                [
                  "c"
                ]
              ]
            ],
            [
              ", "
            ],
            [
              "#ifndef",
              [
                [
                  "c"
                ]
              ]
            ],
            [
              ", "
            ],
            [
              "#endif",
              [
                [
                  "c"
                ]
              ]
            ],
            [
              " directives."
            ]
          ]
        },
        "type": "text",
        "version": 1,
        "inline_content": [
          {
            "Text": "Multiple inclusion is prevented using “include guards”, which are sometimes also known as header guards or macro guards. These are implemented using the preprocessor "
          },
          {
            "Text": "#define",
            "AttrFlags": 2
          },
          {
            "Text": ", "
          },
          {
            "Text": "#ifndef",
            "AttrFlags": 2
          },
          {
            "Text": ", "
          },
          {
            "Text": "#endif",
            "AttrFlags": 2
          },
          {
            "Text": " directives."
          }
        ]
      },
      {
        "alive": true,
        "created_by": "bb760e2d-d679-4b64-b2a9-03005b21870a",
        "created_time": 1550522298725,
        "id": "bc1f7ae7-afbb-4b1a-a130-bef1da3afe1f",
        "ignore_block_count": true,
        "last_edited_by": "bb760e2d-d679-4b64-b2a9-03005b21870a",
        "last_edited_time": 1550522298725,
        "parent_id": "4f6441ec-a8f8-4e36-ab7c-b03f37c7ca89",
        "parent_table": "block",
        "properties": {
          "title": [
            [
              "e.g."
            ]
          ]
        },
        "type": "text",
        "version": 1,
        "inline_content": [
          {
            "Text": "e.g."
          }
        ]
      },
      {
        "alive": true,
        "created_by": "bb760e2d-d679-4b64-b2a9-03005b21870a",
        "created_time": 1550522298725,
        "id": "2282b347-fc0e-4d1b-8605-0d061141a8e2",
        "ignore_block_count": true,
        "last_edited_by": "bb760e2d-d679-4b64-b2a9-03005b21870a",
        "last_edited_time": 1550522298725,
        "parent_id": "4f6441ec-a8f8-4e36-ab7c-b03f37c7ca89",
        "parent_table": "block",
        "properties": {
          "language": [
            [
              "Plain Text"
            ]
          ],
          "title": [
            [
              "// Foo.h\n#ifndef FOO_H_INCLUDED \n#define FOO_H_INCLUDED\n\nclass Foo    //  a class definition\n{\n};\n\n#endif"
            ]
          ]
        },
        "type": "code",
        "version": 1,
        "code": "// Foo.h\n#ifndef FOO_H_INCLUDED \n#define FOO_H_INCLUDED\n\nclass Foo    //  a class definition\n{\n};\n\n#endif",
        "code_language": "Plain Text"
      },
      {
        "alive": true,
        "created_by": "bb760e2d-d679-4b64-b2a9-03005b21870a",
        "created_time": 1550522298726,
        "id": "c485d9fa-dc6b-43ed-905b-1ea7ab9644d3",
        "ignore_block_count": true,
        "last_edited_by": "bb760e2d-d679-4b64-b2a9-03005b21870a",
        "last_edited_time": 1550522298726,
        "parent_id": "4f6441ec-a8f8-4e36-ab7c-b03f37c7ca89",
        "parent_table": "block",
        "properties": {
          "title": [
            [
              "The key advantage of using include guards is that they will work with all standard-compliant compilers and preprocessors."
            ]
          ]
        },
        "type": "text",
        "version": 1,
        "inline_content": [
          {
            "Text": "The key advantage of using include guards is that they will work with all standard-compliant compilers and preprocessors."
          }
        ]
      },
      {
        "alive": true,
        "created_by": "bb760e2d-d679-4b64-b2a9-03005b21870a",
        "created_time": 1550522298726,
        "id": "2aeba1ed-f284-4404-b9c2-1a3a4eef204d",
        "ignore_block_count": true,
        "last_edited_by": "bb760e2d-d679-4b64-b2a9-03005b21870a",
        "last_edited_time": 1550522298726,
        "parent_id": "4f6441ec-a8f8-4e36-ab7c-b03f37c7ca89",
        "parent_table": "block",
        "properties": {
          "title": [
            [
              "However, include guards also cause some problems for developers, as it is necessary to ensure the macros are unique within all headers used in a project. Specifically, if two (or more) headers use "
            ],
            [
              "FOO_H_INCLUDED",
              [
                [
                  "c"
                ]
              ]
            ],
            [
              " as their include guard, the first of those headers included in a compilation unit will effectively prevent the others from being included. Particular challenges are introduced if a project uses a number of third-party libraries with header files that happen to use include guards in common."
            ]
          ]
        },
        "type": "text",
        "version": 1,
        "inline_content": [
          {
            "Text": "However, include guards also cause some problems for developers, as it is necessary to ensure the macros are unique within all headers used in a project. Specifically, if two (or more) headers use "
          },
          {
            "Text": "FOO_H_INCLUDED",
            "AttrFlags": 2
          },
          {
            "Text": " as their include guard, the first of those headers included in a compilation unit will effectively prevent the others from being included. Particular challenges are introduced if a project uses a number of third-party libraries with header files that happen to use include guards in common."
          }
        ]
      },
      {
        "alive": true,
        "created_by": "bb760e2d-d679-4b64-b2a9-03005b21870a",
        "created_time": 1550522298726,
        "id": "1ada0a9e-948a-489c-a0a6-b29db32b4c0a",
        "ignore_block_count": true,
        "last_edited_by": "bb760e2d-d679-4b64-b2a9-03005b21870a",
        "last_edited_time": 1550522298726,
        "parent_id": "4f6441ec-a8f8-4e36-ab7c-b03f37c7ca89",
        "parent_table": "block",
        "properties": {
          "title": [
            [
              "It is also necessary to ensure that the macros used in include guards do not conflict with any other macros defined in header files."
            ]
          ]
        },
        "type": "text",
        "version": 1,
        "inline_content": [
          {
            "Text": "It is also necessary to ensure that the macros used in include guards do not conflict with any other macros defined in header files."
          }
        ]
      },
      {
        "alive": true,
        "created_by": "bb760e2d-d679-4b64-b2a9-03005b21870a",
        "created_time": 1550522298729,
        "id": "b0970e9b-1236-4428-ae7f-0b4e7c075c0f",
        "ignore_block_count": true,
        "last_edited_by": "bb760e2d-d679-4b64-b2a9-03005b21870a",
        "last_edited_time": 1550522298729,
        "parent_id": "4f6441ec-a8f8-4e36-ab7c-b03f37c7ca89",
        "parent_table": "block",
        "properties": {
          "title": [
            [
              "Most C++ implementations",
              [
                [
                  "a",
                  "https://en.wikipedia.org/wiki/Pragma_once#Portability"
                ]
              ]
            ],
            [
              " also support the "
            ],
            [
              "#pragma once",
              [
                [
                  "c"
                ]
              ]
            ],
            [
              " directive which ensures the file is only included once within a single compilation. This is a "
            ],
            [
              "de facto",
              [
                [
                  "i"
                ],
                [
                  "a",
                  "https://en.wikipedia.org/wiki/De_facto_standard"
                ]
              ]
            ],
            [
              " standard",
              [
                [
                  "a",
                  "https://en.wikipedia.org/wiki/De_facto_standard"
                ]
              ]
            ],
            [
              " directive, but it is not part of any ISO C++ standard. For example:"
            ]
          ]
        },
        "type": "text",
        "version": 1,
        "inline_content": [
          {
            "Text": "Most C++ implementations",
            "Link": "https://en.wikipedia.org/wiki/Pragma_once#Portability"
          },
          {
            "Text": " also support the "
          },
          {
            "Text": "#pragma once",
            "AttrFlags": 2
          },
          {
            "Text": " directive which ensures the file is only included once within a single compilation. This is a "
          },
          {
            "Text": "de facto",
            "AttrFlags": 4,
            "Link": "https://en.wikipedia.org/wiki/De_facto_standard"
          },
          {
            "Text": " standard",
            "Link": "https://en.wikipedia.org/wiki/De_facto_standard"
          },
          {
            "Text": " directive, but it is not part of any ISO C++ standard. For example:"
          }
        ]
      },
      {
        "alive": true,
        "created_by": "bb760e2d-d679-4b64-b2a9-03005b21870a",
        "created_time": 1550522298730,
        "id": "9a3c0368-2480-4f05-b741-77503d33ddad",
        "ignore_block_count": true,
        "last_edited_by": "bb760e2d-d679-4b64-b2a9-03005b21870a",
        "last_edited_time": 1550522298730,
        "parent_id": "4f6441ec-a8f8-4e36-ab7c-b03f37c7ca89",
        "parent_table": "block",
        "properties": {
          "language": [
            [
              "Plain Text"
            ]
          ],
          "title": [
            [
              "// Foo.h\n#pragma once\n\nclass Foo\n{\n};"
            ]
          ]
        },
        "type": "code",
        "version": 1,
        "code": "// Foo.h\n#pragma once\n\nclass Foo\n{\n};",
        "code_language": "Plain Text"
      },
      {
        "alive": true,
        "created_by": "bb760e2d-d679-4b64-b2a9-03005b21870a",
        "created_time": 1550522298730,
        "id": "0144877d-1baf-4d31-abba-9947a7b0eb8b",
        "ignore_block_count": true,
        "last_edited_by": "bb760e2d-d679-4b64-b2a9-03005b21870a",
        "last_edited_time": 1550522298730,
        "parent_id": "4f6441ec-a8f8-4e36-ab7c-b03f37c7ca89",
        "parent_table": "block",
        "properties": {
          "title": [
            [
              "While "
            ],
            [
              "#pragma once",
              [
                [
                  "c"
                ]
              ]
            ],
            [
              " avoids some problems associated with include guards, a "
            ],
            [
              "#pragma",
              [
                [
                  "c"
                ]
              ]
            ],
            [
              " - by definition in the standards - is inherently a compiler-specific hook, and will be silently ignored by compilers that don’t support it. Projects which use "
            ],
            [
              "#pragma once",
              [
                [
                  "c"
                ]
              ]
            ],
            [
              " are more difficult to port to compilers that don’t support it."
            ]
          ]
        },
        "type": "text",
        "version": 1,
        "inline_content": [
          {
            "Text": "While "
          },
          {
            "Text": "#pragma once",
            "AttrFlags": 2
          },
          {
            "Text": " avoids some problems associated with include guards, a "
          },
          {
            "Text": "#pragma",
            "AttrFlags": 2
          },
          {
            "Text": " - by definition in the standards - is inherently a compiler-specific hook, and will be silently ignored by compilers that don’t support it. Projects which use "
          },
          {
            "Text": "#pragma once",
            "AttrFlags": 2
          },
          {
            "Text": " are more difficult to port to compilers that don’t support it."
          }
        ]
      },
      {
        "alive": true,
        "created_by": "bb760e2d-d679-4b64-b2a9-03005b21870a",
        "created_time": 1550522298730,
        "id": "6f4a90d3-bbdf-4562-a326-ef73a431f69e",
        "ignore_block_count": true,
        "last_edited_by": "bb760e2d-d679-4b64-b2a9-03005b21870a",
        "last_edited_time": 1550522298730,
        "parent_id": "4f6441ec-a8f8-4e36-ab7c-b03f37c7ca89",
        "parent_table": "block",
        "properties": {
          "title": [
            [
              "A number of coding guidelines and assurance standards for C++ specifically discourage any use of the preprocessor other than to "
            ],
            [
              "#include",
              [
                [
                  "c"
                ]
              ]
            ],
            [
              " header files or for the purposes of placing include guards in headers."
            ]
          ]
        },
        "type": "text",
        "version": 1,
        "inline_content": [
          {
            "Text": "A number of coding guidelines and assurance standards for C++ specifically discourage any use of the preprocessor other than to "
          },
          {
            "Text": "#include",
            "AttrFlags": 2
          },
          {
            "Text": " header files or for the purposes of placing include guards in headers."
          }
        ]
      }
    ],
    "title": "Include Guards",
    "format_page": {
      "page_cover": "",
      "page_cover_position": 0,
      "page_font": "",
      "page_full_width": true,
      "page_icon": "",
      "page_small_text": true
    }
  },
  "Users": [
    {
      "email": "kkowalczyk@gmail.com",
      "family_name": "Kowalczyk",
      "given_name": "Krzysztof",
      "id": "bb760e2d-d679-4b64-b2a9-03005b21870a",
      "locale": "en",
      "mobile_onboarding_completed": true,
      "onboarding_completed": true,
      "profile_photo": "https://s3-us-west-2.amazonaws.com/public.notion-static.com/2dcaa66c-7674-4ff6-9924-601785b63561/head-bw-640x960.png",
      "time_zone": "America/Los_Angeles",
      "version": 19
    }
  ],
  "Tables": null
}